{
   "took": 2178,
   "timed_out": false,
   "_shards": {
      "total": 30,
      "successful": 30,
      "skipped": 0,
      "failed": 0
   },
   "hits": {
      "total": 234850,
      "max_score": 0.0,
      "hits": [
         {
            "_index": "anal_product_brand_2020-02",
            "_type": "_doc",
            "_id": "TyE7E3MBX67z3QWDpVEQ",
            "_score": 0.0,
            "_routing": "b10e156b-2bd6-451c-8378-aacf8b6c16f8",
            "_source": {
               "user_info": [
                  "G63573442,1",
                  "G7984955,1"
               ],
               "time_type": "w",
               "motivation": 0,
               "end_date": "2020-02-01",
               "start_date": "2020-02-01",
               "category": "lv1_b",
               "uuid": "b10e156b-2bd6-451c-8378-aacf8b6c16f8",
               "hr": 12,
               "name": "保健食品/用品||BioJoy百喬"
            }
         },
         {
            "_index": "anal_product_brand_2020-02",
            "_type": "_doc",
            "_id": "aSE7E3MBX67z3QWDpVEQ",
            "_score": 0.0,
            "_routing": "2dfa59ea-e444-4929-94c5-2e19b881f07b",
            "_source": {
               "user_info": [
                  "G60792724,1",
                  "G62328556,2",
                  "G63151948,1",
                  "G53802736,3",
                  "G63533360,1",
                  "G47931370,1",
                  "G62811526,1",
                  "G64110671,3"
               ],
               "time_type": "w",
               "motivation": 0,
               "end_date": "2020-02-01",
               "start_date": "2020-02-01",
               "category": "lv1_b",
               "uuid": "2dfa59ea-e444-4929-94c5-2e19b881f07b",
               "hr": -1,
               "name": "資訊電腦||贈Wifi 6無線分享器"
            }
         },
         {
            "_index": "anal_product_brand_2020-02",
            "_type": "_doc",
            "_id": "pSE7E3MBX67z3QWDpVEQ",
            "_score": 0.0,
            "_routing": "389fee0d-ddfd-45ae-ac64-aa2c627354e0",
            "_source": {
               "user_info": [
                  "G60607884,1"
               ],
               "time_type": "w",
               "motivation": 0,
               "end_date": "2020-02-01",
               "start_date": "2020-02-01",
               "category": "lv1_b",
               "uuid": "389fee0d-ddfd-45ae-ac64-aa2c627354e0",
               "hr": 16,
               "name": "食品飲料||台灣茶奶茶"
            }
         },
         {
            "_index": "anal_product_brand_2020-02",
            "_type": "_doc",
            "_id": "wCE7E3MBX67z3QWDpVEQ",
            "_score": 0.0,
            "_routing": "4718a3f3-fc74-4303-ae47-0decf100b641",
            "_source": {
               "user_info": [
                  "G62297652,2"
               ],
               "time_type": "w",
               "motivation": 0,
               "end_date": "2020-02-01",
               "start_date": "2020-02-01",
               "category": "lv1_b",
               "uuid": "4718a3f3-fc74-4303-ae47-0decf100b641",
               "hr": 12,
               "name": "傢俱||魔術大空間"
            }
         },
         {
            "_index": "anal_product_brand_2020-02",
            "_type": "_doc",
            "_id": "FyE7E3MBX67z3QWDpVMQ",
            "_score": 0.0,
            "_routing": "98e75ac2-fdac-4ef7-85f7-e6519812efdd",
            "_source": {
               "user_info": [
                  "G5276831,1"
               ],
               "time_type": "w",
               "motivation": 0,
               "end_date": "2020-02-01",
               "start_date": "2020-02-01",
               "category": "lv1_b",
               "uuid": "98e75ac2-fdac-4ef7-85f7-e6519812efdd",
               "hr": 21,
               "name": "餐廚用品||AKWATEK"
            }
         },
         {
            "_index": "anal_product_brand_2020-02",
            "_type": "_doc",
            "_id": "zSE7E3MBX67z3QWDpVMQ",
            "_score": 0.0,
            "_routing": "e8fe62f4-47a4-4c86-bd9b-b9bdda7cb768",
            "_source": {
               "user_info": [
                  "G56674021,4"
               ],
               "time_type": "w",
               "motivation": 0,
               "end_date": "2020-02-01",
               "start_date": "2020-02-01",
               "category": "lv1_b",
               "uuid": "e8fe62f4-47a4-4c86-bd9b-b9bdda7cb768",
               "hr": 15,
               "name": "服裝內著||Solara 索菈娜"
            }
         },
         {
            "_index": "anal_product_brand_2020-02",
            "_type": "_doc",
            "_id": "HCE7E3MBX67z3QWDpVUQ",
            "_score": 0.0,
            "_routing": "d400855d-01d8-4222-9816-5c16321a3acd",
            "_source": {
               "user_info": [
                  "G62967483,1"
               ],
               "time_type": "w",
               "motivation": 0,
               "end_date": "2020-02-01",
               "start_date": "2020-02-01",
               "category": "lv1_b",
               "uuid": "d400855d-01d8-4222-9816-5c16321a3acd",
               "hr": 8,
               "name": "運動用品/器材||PUSH!"
            }
         },
         {
            "_index": "anal_product_brand_2020-02",
            "_type": "_doc",
            "_id": "diE7E3MBX67z3QWDpVUQ",
            "_score": 0.0,
            "_routing": "9be2a115-159c-45ca-acfc-e429a115502c",
            "_source": {
               "user_info": [
                  "G55502720,1"
               ],
               "time_type": "w",
               "motivation": 2,
               "end_date": "2020-02-01",
               "start_date": "2020-02-01",
               "category": "lv1_b",
               "uuid": "9be2a115-159c-45ca-acfc-e429a115502c",
               "hr": 14,
               "name": "母嬰/童||鑫耀生技"
            }
         },
         {
            "_index": "anal_product_brand_2020-02",
            "_type": "_doc",
            "_id": "4yE7E3MBX67z3QWDpVUQ",
            "_score": 0.0,
            "_routing": "082bfa31-3b73-44d5-acdb-3ab40ce85b16",
            "_source": {
               "user_info": [
                  "G61242992,1"
               ],
               "time_type": "w",
               "motivation": 0,
               "end_date": "2020-02-01",
               "start_date": "2020-02-01",
               "category": "lv1_b",
               "uuid": "082bfa31-3b73-44d5-acdb-3ab40ce85b16",
               "hr": 18,
               "name": "運動用品/器材||arena"
            }
         },
         {
            "_index": "anal_product_brand_2020-02",
            "_type": "_doc",
            "_id": "_iE7E3MBX67z3QWDpVUQ",
            "_score": 0.0,
            "_routing": "ee895119-1b37-4c15-b975-e3132bc8870a",
            "_source": {
               "user_info": [
                  "G62269940,2",
                  "G63799027,4"
               ],
               "time_type": "w",
               "motivation": 0,
               "end_date": "2020-02-01",
               "start_date": "2020-02-01",
               "category": "lv1_b",
               "uuid": "ee895119-1b37-4c15-b975-e3132bc8870a",
               "hr": 15,
               "name": "手機  ||CORAL/ODEL"
            }
         }
      ]
   },
   "aggregations": {
      "test": {
         "value": {
            "園藝": {
               "所有人數": 252,
               "受眾人數": 0,
               "受眾次數": 0,
               "所有次數": 1972
            },
            "傢俱": {
               "所有人數": 8696,
               "受眾人數": 10,
               "受眾次數": 183,
               "所有次數": 114062
            },
            "車類": {
               "所有人數": 3499,
               "受眾人數": 4,
               "受眾次數": 12,
               "所有次數": 23282
            },
            "旅遊行程/用品": {
               "所有人數": 766,
               "受眾人數": 1,
               "受眾次數": 6,
               "所有次數": 4620
            },
            "手機  ": {
               "所有人數": 9447,
               "受眾人數": 7,
               "受眾次數": 104,
               "所有次數": 78742
            },
            "修繕裝潢": {
               "所有人數": 4163,
               "受眾人數": 1,
               "受眾次數": 2,
               "所有次數": 31320
            },
            "母嬰/童": {
               "所有人數": 10374,
               "受眾人數": 6,
               "受眾次數": 233,
               "所有次數": 105392
            },
            "家電": {
               "所有人數": 23193,
               "受眾人數": 15,
               "受眾次數": 229,
               "所有次數": 221132
            },
            "運動用品/器材": {
               "所有人數": 1702,
               "受眾人數": 2,
               "受眾次數": 23,
               "所有次數": 12630
            },
            "文具樂器": {
               "所有人數": 1987,
               "受眾人數": 2,
               "受眾次數": 4,
               "所有次數": 19606
            },
            "數位內容": {
               "所有人數": 476,
               "受眾人數": 1,
               "受眾次數": 2,
               "所有次數": 3164
            },
            "飾品配件": {
               "所有人數": 4898,
               "受眾人數": 4,
               "受眾次數": 55,
               "所有次數": 51420
            },
            "彩妝保養": {
               "所有人數": 14077,
               "受眾人數": 8,
               "受眾次數": 46,
               "所有次數": 166896
            },
            "家庭清潔/紙品": {
               "所有人數": 10071,
               "受眾人數": 8,
               "受眾次數": 44,
               "所有次數": 99536
            },
            "寵物": {
               "所有人數": 2186,
               "受眾人數": 2,
               "受眾次數": 59,
               "所有次數": 22146
            },
            "票券": {
               "所有人數": 2045,
               "受眾人數": 1,
               "受眾次數": 9,
               "所有次數": 12014
            },
            "珠寶/貴金屬": {
               "所有人數": 2020,
               "受眾人數": 3,
               "受眾次數": 54,
               "所有次數": 22516
            },
            "momo專案": {
               "所有人數": 359,
               "受眾人數": 0,
               "受眾次數": 0,
               "所有次數": 2972
            },
            "按摩器材": {
               "所有人數": 1129,
               "受眾人數": 1,
               "受眾次數": 2,
               "所有次數": 8714
            },
            "生鮮": {
               "所有人數": 2488,
               "受眾人數": 1,
               "受眾次數": 6,
               "所有次數": 24748
            },
            "圖書/影音": {
               "所有人數": 6747,
               "受眾人數": 5,
               "受眾次數": 36,
               "所有次數": 61286
            },
            "藝術開運/宗教": {
               "所有人數": 1408,
               "受眾人數": 0,
               "受眾次數": 0,
               "所有次數": 13636
            },
            "服裝內著": {
               "所有人數": 21518,
               "受眾人數": 10,
               "受眾次數": 314,
               "所有次數": 292466
            },
            "餐廚用品": {
               "所有人數": 12714,
               "受眾人數": 9,
               "受眾次數": 44,
               "所有次數": 133900
            },
            "食品飲料": {
               "所有人數": 9561,
               "受眾人數": 8,
               "受眾次數": 55,
               "所有次數": 137816
            },
            "個人清潔": {
               "所有人數": 8621,
               "受眾人數": 4,
               "受眾次數": 24,
               "所有次數": 102344
            },
            "寢具傢飾": {
               "所有人數": 14882,
               "受眾人數": 8,
               "受眾次數": 157,
               "所有次數": 182848
            },
            "鞋/包/箱": {
               "所有人數": 23432,
               "受眾人數": 8,
               "受眾次數": 31,
               "所有次數": 284774
            },
            "保健食品/用品": {
               "所有人數": 13939,
               "受眾人數": 7,
               "受眾次數": 57,
               "所有次數": 111438
            },
            "戶外用品": {
               "所有人數": 2424,
               "受眾人數": 2,
               "受眾次數": 18,
               "所有次數": 20146
            },
            "資訊電腦": {
               "所有人數": 3698,
               "受眾人數": 6,
               "受眾次數": 41,
               "所有次數": 28718
            },
            "攝影器材": {
               "所有人數": 1277,
               "受眾人數": 0,
               "受眾次數": 0,
               "所有次數": 9502
            }
         }
      }
   }
}

